{
  "meta": {
    "scanned_at_bj": "2026-03-20T14:47:58.468Z",
    "session": "PM",
    "trend_summary": {
      "VIRAL_GIANT": 1,
      "CODE_LEVERAGE": 2,
      "TALENT_GROWTH": 5,
      "VIRAL_UNCATEGORIZED": 16,
      "KNOWLEDGE_BASE": 3,
      "TECH_ACCELERATOR": 1
    }
  },
  "items": [
    {
      "name": "math-inc/OpenGauss",
      "stars": 270,
      "tags": [
        "VIRAL_GIANT"
      ],
      "reason": "FORCE_KEEP",
      "url": "https://github.com/math-inc/OpenGauss"
    },
    {
      "name": "truongduy2611/app-store-preflight-skills",
      "stars": 260,
      "tags": [
        "CODE_LEVERAGE",
        "TALENT_GROWTH"
      ],
      "reason": "STRATEGY",
      "url": "https://github.com/truongduy2611/app-store-preflight-skills"
    },
    {
      "name": "stvlynn/dingtalk-wukong-skills",
      "stars": 81,
      "tags": [
        "CODE_LEVERAGE",
        "TALENT_GROWTH",
        "KNOWLEDGE_BASE"
      ],
      "reason": "STRATEGY",
      "url": "https://github.com/stvlynn/dingtalk-wukong-skills"
    },
    {
      "name": "dharshini1316/StratusIQ",
      "stars": 45,
      "tags": [
        "TECH_ACCELERATOR"
      ],
      "reason": "STRATEGY",
      "url": "https://github.com/dharshini1316/StratusIQ"
    }
  ]
}