{
  "meta": {
    "scanned_at_bj": "2026-06-23T00:45:40.565Z",
    "total_captured": 20,
    "TRENDING_DIRECTIONS": [
      "ENCODE (Heat:918)",
      "Feature learning (Heat:918)",
      "Heuristics (Heat:918)",
      "Graph (Heat:918)",
      "Kernel method (Heat:918)"
    ],
    "strategy_summary": {
      "BIO_REVOLUTION": 12,
      "NEXT_COMPUTING": 8,
      "AI_CORE": 3
    }
  },
  "items": [
    {
      "title": "RhizoDB: A Bounded Activation-Flow Architecture for Graph-Based Memory Systems",
      "type": "⚡ EARLY_SIGNAL",
      "journal": "Zenodo (CERN European Organization for Nuclear Research)",
      "metrics": {
        "citations": 917,
        "impact_factor": "0.0"
      },
      "strategies": [
        "BIO_REVOLUTION"
      ],
      "url": "https://doi.org/10.5281/zenodo.20695702",
      "reason": "Velocity: 917 citations",
      "publication_date": "2026-06-15"
    },
    {
      "title": "Large AdS black holes from QFT",
      "type": "⚡ EARLY_SIGNAL",
      "journal": "Journal of the Korean Physical Society",
      "metrics": {
        "citations": 58,
        "impact_factor": "0.0"
      },
      "strategies": [
        "NEXT_COMPUTING"
      ],
      "url": "https://link.springer.com/content/pdf/10.1007/s40042-026-01671-z.pdf",
      "reason": "Velocity: 58 citations",
      "publication_date": "2026-06-19"
    },
    {
      "title": "Analysis Is Topology: The Intrinsic Identity of Gradient Flow and Topological Charge in Dynamic Complex Analysis",
      "type": "⚡ EARLY_SIGNAL",
      "journal": "Zenodo (CERN European Organization for Nuclear Research)",
      "metrics": {
        "citations": 25,
        "impact_factor": "0.0"
      },
      "strategies": [
        "NEXT_COMPUTING"
      ],
      "url": "https://doi.org/10.5281/zenodo.20694976",
      "reason": "Velocity: 25 citations",
      "publication_date": "2026-06-15"
    },
    {
      "title": "Quantum State Preparation without Coherent Arithmetic",
      "type": "⚡ EARLY_SIGNAL",
      "journal": "Physical Review Letters",
      "metrics": {
        "citations": 18,
        "impact_factor": "0.0"
      },
      "strategies": [
        "NEXT_COMPUTING"
      ],
      "url": "https://arxiv.org/pdf/2210.14892",
      "reason": "Velocity: 18 citations",
      "publication_date": "2026-06-18"
    },
    {
      "title": "Non-Abelian Emergence: A Generative Derivation from Axioms to Gauge Field Theory",
      "type": "⚡ EARLY_SIGNAL",
      "journal": "Zenodo (CERN European Organization for Nuclear Research)",
      "metrics": {
        "citations": 17,
        "impact_factor": "0.0"
      },
      "strategies": [
        "AI_CORE",
        "BIO_REVOLUTION",
        "NEXT_COMPUTING"
      ],
      "url": "https://doi.org/10.5281/zenodo.20712118",
      "reason": "Velocity: 17 citations",
      "publication_date": "2026-06-16"
    },
    {
      "title": "The Minimal Discrete Geometry",
      "type": "⚡ EARLY_SIGNAL",
      "journal": "Zenodo (CERN European Organization for Nuclear Research)",
      "metrics": {
        "citations": 16,
        "impact_factor": "0.0"
      },
      "strategies": [
        "BIO_REVOLUTION"
      ],
      "url": "https://doi.org/10.5281/zenodo.19433595",
      "reason": "Velocity: 16 citations",
      "publication_date": "2026-06-21"
    },
    {
      "title": "UGP Physics program — public Zenodo catalog",
      "type": "⚡ EARLY_SIGNAL",
      "journal": "Zenodo (CERN European Organization for Nuclear Research)",
      "metrics": {
        "citations": 16,
        "impact_factor": "0.0"
      },
      "strategies": [
        "AI_CORE",
        "BIO_REVOLUTION"
      ],
      "url": "https://doi.org/10.5281/zenodo.20168144",
      "reason": "Velocity: 16 citations",
      "publication_date": "2026-06-21"
    },
    {
      "title": "From Auditability to Redundant Records: Public Finality in a Consistency-Constrained Information History",
      "type": "⚡ EARLY_SIGNAL",
      "journal": "Zenodo (CERN European Organization for Nuclear Research)",
      "metrics": {
        "citations": 14,
        "impact_factor": "0.0"
      },
      "strategies": [
        "NEXT_COMPUTING"
      ],
      "url": "https://doi.org/10.5281/zenodo.20724948",
      "reason": "Velocity: 14 citations",
      "publication_date": "2026-06-17"
    },
    {
      "title": "Geometric Accretion Limits in Early Universe Supermassive Black Holes: A Falsifiable Prediction from Information Tension Theory",
      "type": "⚡ EARLY_SIGNAL",
      "journal": "Zenodo (CERN European Organization for Nuclear Research)",
      "metrics": {
        "citations": 13,
        "impact_factor": "0.0"
      },
      "strategies": [
        "BIO_REVOLUTION"
      ],
      "url": "https://doi.org/10.5281/zenodo.20776361",
      "reason": "Velocity: 13 citations",
      "publication_date": "2026-06-20"
    },
    {
      "title": "KOKU Bioquartz Ecosystem: Technology Overview and Partnership Proposal — Implantable Cardiac Resonance Device, Bioquartz Watch, and Wrist-Worn Bidirectional Resonance System",
      "type": "⚡ EARLY_SIGNAL",
      "journal": "Zenodo (CERN European Organization for Nuclear Research)",
      "metrics": {
        "citations": 12,
        "impact_factor": "0.0"
      },
      "strategies": [
        "BIO_REVOLUTION"
      ],
      "url": "https://doi.org/10.5281/zenodo.20709224",
      "reason": "Velocity: 12 citations",
      "publication_date": "2026-06-16"
    },
    {
      "title": "Delayed Finality and the Black Hole Information Problem",
      "type": "⚡ EARLY_SIGNAL",
      "journal": "Zenodo (CERN European Organization for Nuclear Research)",
      "metrics": {
        "citations": 12,
        "impact_factor": "0.0"
      },
      "strategies": [
        "NEXT_COMPUTING"
      ],
      "url": "https://doi.org/10.5281/zenodo.20728612",
      "reason": "Velocity: 12 citations",
      "publication_date": "2026-06-17"
    },
    {
      "title": "The Biogenic Engine: Wave, Generation, and Heartbeat as a Closed-Loop V=N/D System",
      "type": "⚡ EARLY_SIGNAL",
      "journal": "Zenodo (CERN European Organization for Nuclear Research)",
      "metrics": {
        "citations": 12,
        "impact_factor": "0.0"
      },
      "strategies": [
        "BIO_REVOLUTION"
      ],
      "url": "https://doi.org/10.5281/zenodo.20697246",
      "reason": "Velocity: 12 citations",
      "publication_date": "2026-06-15"
    },
    {
      "title": "The Dynamic Topology-Algebra Correspondence Principle: From Phase Closure to Galois Theory",
      "type": "⚡ EARLY_SIGNAL",
      "journal": "Zenodo (CERN European Organization for Nuclear Research)",
      "metrics": {
        "citations": 10,
        "impact_factor": "0.0"
      },
      "strategies": [
        "NEXT_COMPUTING"
      ],
      "url": "https://doi.org/10.5281/zenodo.20695659",
      "reason": "Velocity: 10 citations",
      "publication_date": "2026-06-15"
    },
    {
      "title": "A Generativist Reformulation of the Riemann Hypothesis: Self-Dual Emergence, Periodic Spectral Correspondence, and the Inevitability of the Critical Line 1/2",
      "type": "⚡ EARLY_SIGNAL",
      "journal": "Zenodo (CERN European Organization for Nuclear Research)",
      "metrics": {
        "citations": 10,
        "impact_factor": "0.0"
      },
      "strategies": [
        "BIO_REVOLUTION"
      ],
      "url": "https://doi.org/10.5281/zenodo.20741956",
      "reason": "Velocity: 10 citations",
      "publication_date": "2026-06-18"
    },
    {
      "title": "PrismGate, Use Case Demonstration: Credential Management and Service Registration without a Central Identity Database",
      "type": "⚡ EARLY_SIGNAL",
      "journal": "Zenodo (CERN European Organization for Nuclear Research)",
      "metrics": {
        "citations": 10,
        "impact_factor": "0.0"
      },
      "strategies": [
        "NEXT_COMPUTING"
      ],
      "url": "https://doi.org/10.5281/zenodo.20708778",
      "reason": "Velocity: 10 citations",
      "publication_date": "2026-06-16"
    },
    {
      "title": "CPR as Engine Restart: Wave Ignition Precedes Electrical Generation in Cardiac Loop Re-entry",
      "type": "⚡ EARLY_SIGNAL",
      "journal": "Zenodo (CERN European Organization for Nuclear Research)",
      "metrics": {
        "citations": 10,
        "impact_factor": "0.0"
      },
      "strategies": [
        "BIO_REVOLUTION"
      ],
      "url": "https://doi.org/10.5281/zenodo.20701724",
      "reason": "Velocity: 10 citations",
      "publication_date": "2026-06-15"
    },
    {
      "title": "PrismShop, Use Case Demonstration: Anonymous Shopping with Order History, from Login to Delivery",
      "type": "⚡ EARLY_SIGNAL",
      "journal": "Zenodo (CERN European Organization for Nuclear Research)",
      "metrics": {
        "citations": 10,
        "impact_factor": "0.0"
      },
      "strategies": [
        "AI_CORE"
      ],
      "url": "https://doi.org/10.5281/zenodo.20713168",
      "reason": "Velocity: 10 citations",
      "publication_date": "2026-06-16"
    },
    {
      "title": "The Fractal Coupling Flow of the Minimal Discrete Épure",
      "type": "⚡ EARLY_SIGNAL",
      "journal": "Zenodo (CERN European Organization for Nuclear Research)",
      "metrics": {
        "citations": 10,
        "impact_factor": "0.0"
      },
      "strategies": [
        "BIO_REVOLUTION"
      ],
      "url": "https://doi.org/10.5281/zenodo.19630557",
      "reason": "Velocity: 10 citations",
      "publication_date": "2026-06-21"
    },
    {
      "title": "Beckers Collection (Aachen) - Ushabti UB-014: Ushabti of Hori I (Tell Basta)",
      "type": "⚡ EARLY_SIGNAL",
      "journal": "Zenodo (CERN European Organization for Nuclear Research)",
      "metrics": {
        "citations": 9,
        "impact_factor": "0.0"
      },
      "strategies": [
        "BIO_REVOLUTION"
      ],
      "url": "https://doi.org/10.5281/zenodo.19222672",
      "reason": "Velocity: 9 citations",
      "publication_date": "2026-06-18"
    },
    {
      "title": "Machine-Mediated Reception Studies: Charter and Editorial Protocol — A Theology of Error for a Distributed Journal (EA-SEI-MMRS-CHARTER-01 v1.4)",
      "type": "⚡ EARLY_SIGNAL",
      "journal": "Zenodo (CERN European Organization for Nuclear Research)",
      "metrics": {
        "citations": 8,
        "impact_factor": "0.0"
      },
      "strategies": [
        "BIO_REVOLUTION"
      ],
      "url": "https://doi.org/10.5281/zenodo.20722562",
      "reason": "Velocity: 8 citations",
      "publication_date": "2026-06-16"
    }
  ]
}